swc_utils/__init__.py
swc_utils/caching/__init__.py
swc_utils/caching/cache.py
swc_utils/caching/cache_controller.py
swc_utils/caching/caching_service.py
swc_utils/database/__init__.py
swc_utils/database/base_model.py
swc_utils/database/connection_profile.py
swc_utils/database/database_connection.py
swc_utils/database/db_table_care.py
swc_utils/exceptions/__init__.py
swc_utils/exceptions/package_exceptions.py
swc_utils/mail/__init__.py
swc_utils/mail/smtp_client.py
swc_utils/other/__init__.py
swc_utils/other/decorators.py
swc_utils/other/generator_utils.py
swc_utils/redis_db/__init__.py
swc_utils/redis_db/event_manager.py
swc_utils/redis_db/interface.py
swc_utils/routing/__init__.py
swc_utils/routing/auth_routes.py
swc_utils/tools/__init__.py
swc_utils/tools/config.py
swc_utils/tools/package_repo.py
swc_utils/tools/route_loader.py
swc_utils/tools/wsgi_runner.py
swc_utils/web/__init__.py
swc_utils/web/adv_responses.py
swc_utils/web/auth_manager.py
swc_utils/web/request_codes.py
swc_utils/web/token_api.py
swc_utils/wsl/__init__.py
swc_utils/wsl/wsl_compatability.py
swc_utils-0.10.0.dist-info/licenses/LICENSE
swc_utils-0.10.0.dist-info/METADATA
swc_utils-0.10.0.dist-info/WHEEL
swc_utils-0.10.0.dist-info/top_level.txt
swc_utils-0.10.0.dist-info/RECORD
